pyloginsight/__init__.py
pyloginsight/__version__.py
pyloginsight/abstracts.py
pyloginsight/connection.py
pyloginsight/content.py
pyloginsight/exceptions.py
pyloginsight/ingestion.py
pyloginsight/models.py
pyloginsight/operator.py
pyloginsight/query.py
pyloginsight/updates.py
pyloginsight/cli/__init__.py
pyloginsight/cli/__main__.py
pyloginsight/internal/__init__.py
pyloginsight/internal/auth_providers.py
pyloginsight/internal/internal_config.py
pyloginsight_fork-0.dev0.dist-info/LICENSE
pyloginsight_fork-0.dev0.dist-info/METADATA
pyloginsight_fork-0.dev0.dist-info/WHEEL
pyloginsight_fork-0.dev0.dist-info/entry_points.txt
pyloginsight_fork-0.dev0.dist-info/top_level.txt
pyloginsight_fork-0.dev0.dist-info/RECORD
