Metadata-Version: 2.1
Name: pyloginsight-fork
Version: 0.dev0
Summary: VMware vRealize Log Insight Client
Home-page: http://github.com/vmware/pyloginsight/
Author: Alan Castonguay
Author-email: acastonguay@vmware.com
License: Apache Software License 2.0
Platform: any
Classifier: Programming Language :: Python :: 2.7
Classifier: Programming Language :: Python :: 3.5
Classifier: Development Status :: 1 - Planning
Classifier: Natural Language :: English
Classifier: Intended Audience :: Information Technology
Classifier: Intended Audience :: System Administrators
Classifier: Intended Audience :: Developers
Classifier: License :: OSI Approved :: Apache Software License
Classifier: Operating System :: OS Independent
Classifier: Topic :: Software Development :: Libraries :: Python Modules
Requires-Dist: requests
Requires-Dist: marshmallow
Requires-Dist: attrdict
Requires-Dist: six
Requires-Dist: pytz
